Metadata-Version: 2.1
Name: odoo10-addon-account-analytic-parent
Version: 10.0.1.0.0.99.dev32
Summary: This module reintroduces the hierarchy to the analytic accounts.
Home-page: https://www.github.com/OCA/account-analytic.git
Author: Matmoz d.o.o., Luxim d.o.o., Deneroteam, Eficent, Tecnativa, Odoo Community Association (OCA)
Author-email: support@odoo-community.org
License: AGPL-3
Platform: UNKNOWN
Classifier: Programming Language :: Python
Classifier: Framework :: Odoo
Classifier: Framework :: Odoo :: 10.0
Classifier: License :: OSI Approved :: GNU Affero General Public License v3
Requires-Python: ~=2.7
Requires-Dist: odoo (<10.1dev,>=10.0)
